QPAML/__init__.py
QPAML/biocyc.py
QPAML/config.py
QPAML/core.py
QPAML/flux_variability_based.py
QPAML/functions.py
QPAML/gen_mods_trp.csv
QPAML/iML1515a.xml
QPAML/iML1515a_QPAML.xml
QPAML/keio.csv
QPAML/keio_parsed.csv
QPAML/main.py
QPAML/main_modules.py
QPAML/main_users.py
QPAML/bigg/bigg_bc_manula.csv
QPAML/bigg/bigg_bc_manula_borrame.csv
QPAML/bigg/bigg_models_metabolites.txt
QPAML/bigg/bigg_models_reactions.txt
QPAML/biocyc/compounds.dat
QPAML/biocyc/enzrxns.dat
QPAML/biocyc/genes.dat
QPAML/biocyc/pathways.dat
QPAML/biocyc/promoters.dat
QPAML/biocyc/proteins.dat
QPAML/biocyc/protligandcplxes.dat
QPAML/biocyc/reactions.dat
QPAML/biocyc/regulation.dat
QPAML/biocyc/transunits.dat
QPAML/model/GBDT/df_test.dat
QPAML/model/GBDT/df_train.dat
QPAML/model/GBDT/model_rf.dat
QPAML-1.0.1.dist-info/LICENSE
QPAML-1.0.1.dist-info/METADATA
QPAML-1.0.1.dist-info/WHEEL
QPAML-1.0.1.dist-info/top_level.txt
QPAML-1.0.1.dist-info/RECORD
