Metadata-Version: 2.1
Name: QPAML
Version: 1.0.1
Summary: A package to classify metabolic reactions that affect production of metabolites.
Home-page: https://gitlab.com/amalib/qpaml
Author: Miguel Angel Ramos-Valdovinos
Author-email: miguel.ramos@cinvestav.mx
License: Apache 2.0
Keywords: metabolic engineering,Flux Balance Analysis,Qualitative Perturbation Analysis,Qualitative Lineal Model,Metabolic model
Platform: Platform-Independent
Classifier: Development Status :: 4 - Beta
Requires-Python: ==3.8.0
Requires-Dist: cameo ==0.13.6
Requires-Dist: cobra ==0.22.0
Requires-Dist: MarkupSafe ==2.0.1
Requires-Dist: networkx ==3.1
Requires-Dist: psutil ==5.9.5
Requires-Dist: seaborn ==0.12.2
Requires-Dist: lime ==0.2.0.1
Requires-Dist: scikit-learn ==1.3.0
Requires-Dist: numpy ==1.23.5
Requires-Dist: tqdm ==4.66.1
